setup.py
pushcoapi/__init__.py
pushcoapi/authorize.py
pushcoapi/channel.py
pushcoapi/consts.py
pushcoapi/push.py
pushcoapi/subscription.py
pushcoapi.egg-info/PKG-INFO
pushcoapi.egg-info/SOURCES.txt
pushcoapi.egg-info/dependency_links.txt
pushcoapi.egg-info/not-zip-safe
pushcoapi.egg-info/requires.txt
pushcoapi.egg-info/top_level.txt